{
  "project_info": {
    "project_number": "280651968447",
    "firebase_url": "https://mwb-connect.firebaseio.com",
    "project_id": "mwb-connect",
    "storage_bucket": "mwb-connect.appspot.com"
  },
  "client": [
    {
      "client_info": {
        "mobilesdk_app_id": "1:280651968447:android:bbf6889a22879eb2c4fb0a",
        "android_client_info": {
          "package_name": "com.mwbconnect.app"
        }
      },
      "oauth_client": [
        {
          "client_id": "280651968447-nb1p41b8qsrh3qhch6ja4hlf2lfa15hf.apps.googleusercontent.com",
          "client_type": 3
        }
      ],
      "api_key": [
        {
          "current_key": "AIzaSyBre9YjeRt0nVmeroqVAtJUchCOW7G2G58"
        }
      ],
      "services": {
        "appinvite_service": {
          "other_platform_oauth_client": [
            {
              "client_id": "280651968447-nb1p41b8qsrh3qhch6ja4hlf2lfa15hf.apps.googleusercontent.com",
              "client_type": 3
            }
          ]
        }
      }
    }
  ],
  "configuration_version": "1"
}